odoo8_addon_business_requirement_deliverable_cost-8.0.2.0.0-py2.7-nspkg.pth
odoo8_addon_business_requirement_deliverable_cost-8.0.2.0.0.dist-info/DESCRIPTION.rst
odoo8_addon_business_requirement_deliverable_cost-8.0.2.0.0.dist-info/METADATA
odoo8_addon_business_requirement_deliverable_cost-8.0.2.0.0.dist-info/RECORD
odoo8_addon_business_requirement_deliverable_cost-8.0.2.0.0.dist-info/WHEEL
odoo8_addon_business_requirement_deliverable_cost-8.0.2.0.0.dist-info/metadata.json
odoo8_addon_business_requirement_deliverable_cost-8.0.2.0.0.dist-info/namespace_packages.txt
odoo8_addon_business_requirement_deliverable_cost-8.0.2.0.0.dist-info/top_level.txt
odoo_addons/business_requirement_deliverable_cost/README.rst
odoo_addons/business_requirement_deliverable_cost/__init__.py
odoo_addons/business_requirement_deliverable_cost/__openerp__.py
odoo_addons/business_requirement_deliverable_cost/models/__init__.py
odoo_addons/business_requirement_deliverable_cost/models/business.py
odoo_addons/business_requirement_deliverable_cost/report/__init__.py
odoo_addons/business_requirement_deliverable_cost/report/br_deliverable_cost_report.py
odoo_addons/business_requirement_deliverable_cost/report/br_deliverable_cost_report_view.xml
odoo_addons/business_requirement_deliverable_cost/security/business_requirement_deliverable_security.xml
odoo_addons/business_requirement_deliverable_cost/security/ir.model.access.csv
odoo_addons/business_requirement_deliverable_cost/static/description/icon.png
odoo_addons/business_requirement_deliverable_cost/static/img/bus_req_acl1.png
odoo_addons/business_requirement_deliverable_cost/static/img/bus_req_acl2.png
odoo_addons/business_requirement_deliverable_cost/static/img/bus_req_acl3.png
odoo_addons/business_requirement_deliverable_cost/static/img/bus_req_control.png
odoo_addons/business_requirement_deliverable_cost/tests/__init__.py
odoo_addons/business_requirement_deliverable_cost/tests/test_br.py
odoo_addons/business_requirement_deliverable_cost/views/business.xml
